dual_usb_backup/__init__.py
dual_usb_backup-0.1.0.dist-info/METADATA
dual_usb_backup-0.1.0.dist-info/WHEEL
dual_usb_backup-0.1.0.dist-info/top_level.txt
dual_usb_backup-0.1.0.dist-info/RECORD
